tisgrabber/__init__.py
tisgrabber/cam.py
tisgrabber/enums.py
tisgrabber/exceptions.py
tisgrabber/structs.py
tisgrabber/tisgrabber.py
tisgrabber/wrapper.py
tisgrabber/dll/README.md
tisgrabber/dll/tisgrabber.chm
tisgrabber/dll/tisgrabber.h
tisgrabber/dll/win32/TIS_UDSHL11.dll
tisgrabber/dll/win32/tisgrabber.dll
tisgrabber/dll/x64/TIS_UDSHL11_x64.dll
tisgrabber/dll/x64/tisgrabber_x64.dll
py_tisgrabber-1.0.1.dist-info/LICENSE
py_tisgrabber-1.0.1.dist-info/METADATA
py_tisgrabber-1.0.1.dist-info/WHEEL
py_tisgrabber-1.0.1.dist-info/top_level.txt
py_tisgrabber-1.0.1.dist-info/RECORD
