Metadata-Version: 2.1
Name: py-tisgrabber
Version: 1.0.1
Summary: Wrapper for IC-Imaging-Control by The Imaging source for modern Python.
Author: Bastian Leykauf
Author-email: leykauf@physik.hu-berlin.de
License: MIT License
Project-URL: homepage, https://github.com/hub-gain/py-tisgrabber
Project-URL: repository, https://github.com/hub-gain/py-tisgrabber
Classifier: Programming Language :: Python :: 3
Classifier: Operating System :: Microsoft :: Windows
Requires-Python: >=3.11
License-File: LICENSE
Requires-Dist: numpy >=1.26.2
Provides-Extra: dev
Requires-Dist: black >=22.8.0 ; extra == 'dev'
Requires-Dist: pre-commit >=2.20.0 ; extra == 'dev'
Requires-Dist: flake8 >=5.0.4 ; extra == 'dev'
Requires-Dist: isort >=5.10.1 ; extra == 'dev'
Requires-Dist: Flake8-pyproject >=1.1.0.post0 ; extra == 'dev'
Requires-Dist: setuptools-scm >=6.2 ; extra == 'dev'
Provides-Extra: examples
Requires-Dist: matplotlib >=3.8.2 ; extra == 'examples'
Requires-Dist: opencv-contrib-python >=4.8.1.78 ; extra == 'examples'
Requires-Dist: PyQt5 >=5.15.2 ; extra == 'examples'
